odoo9_addon_project_timesheet_time_control-9.0.1.0.1-py2.7-nspkg.pth
odoo9_addon_project_timesheet_time_control-9.0.1.0.1.dist-info/DESCRIPTION.rst
odoo9_addon_project_timesheet_time_control-9.0.1.0.1.dist-info/METADATA
odoo9_addon_project_timesheet_time_control-9.0.1.0.1.dist-info/RECORD
odoo9_addon_project_timesheet_time_control-9.0.1.0.1.dist-info/WHEEL
odoo9_addon_project_timesheet_time_control-9.0.1.0.1.dist-info/metadata.json
odoo9_addon_project_timesheet_time_control-9.0.1.0.1.dist-info/namespace_packages.txt
odoo9_addon_project_timesheet_time_control-9.0.1.0.1.dist-info/top_level.txt
odoo_addons/project_timesheet_time_control/README.rst
odoo_addons/project_timesheet_time_control/__init__.py
odoo_addons/project_timesheet_time_control/__openerp__.py
odoo_addons/project_timesheet_time_control/hooks.py
odoo_addons/project_timesheet_time_control/i18n/ar.po
odoo_addons/project_timesheet_time_control/i18n/bg.po
odoo_addons/project_timesheet_time_control/i18n/bs.po
odoo_addons/project_timesheet_time_control/i18n/ca.po
odoo_addons/project_timesheet_time_control/i18n/cs.po
odoo_addons/project_timesheet_time_control/i18n/de.po
odoo_addons/project_timesheet_time_control/i18n/el.po
odoo_addons/project_timesheet_time_control/i18n/el_GR.po
odoo_addons/project_timesheet_time_control/i18n/en_GB.po
odoo_addons/project_timesheet_time_control/i18n/es.po
odoo_addons/project_timesheet_time_control/i18n/es_AR.po
odoo_addons/project_timesheet_time_control/i18n/es_CR.po
odoo_addons/project_timesheet_time_control/i18n/es_EC.po
odoo_addons/project_timesheet_time_control/i18n/es_MX.po
odoo_addons/project_timesheet_time_control/i18n/es_VE.po
odoo_addons/project_timesheet_time_control/i18n/et.po
odoo_addons/project_timesheet_time_control/i18n/fi.po
odoo_addons/project_timesheet_time_control/i18n/fr.po
odoo_addons/project_timesheet_time_control/i18n/fr_CA.po
odoo_addons/project_timesheet_time_control/i18n/fr_FR.po
odoo_addons/project_timesheet_time_control/i18n/gl.po
odoo_addons/project_timesheet_time_control/i18n/hr.po
odoo_addons/project_timesheet_time_control/i18n/hr_HR.po
odoo_addons/project_timesheet_time_control/i18n/hu.po
odoo_addons/project_timesheet_time_control/i18n/id.po
odoo_addons/project_timesheet_time_control/i18n/it.po
odoo_addons/project_timesheet_time_control/i18n/ja.po
odoo_addons/project_timesheet_time_control/i18n/ko.po
odoo_addons/project_timesheet_time_control/i18n/lt.po
odoo_addons/project_timesheet_time_control/i18n/lv.po
